{
  "Bob Dylan Live Aid Performance 1": {
    "artist": "Bob Dylan",
    "wikidata_artist": "http://www.wikidata.org/entity/Q392",
    "wikidata_event": "http://www.wikidata.org/entity/Q184199",
    "wikipedia_event": "https://en.wikipedia.org/wiki/Live_Aid",
    "wikipedia_artist": ""
  },
  "Bryan Adams Live Aid Performance 1": {
    "artist": "Bryan Adams",
    "wikidata_artist": "http://www.wikidata.org/entity/Q482907",
    "wikidata_event": "http://www.wikidata.org/entity/Q184199",
    "wikipedia_event": "https://en.wikipedia.org/wiki/Live_Aid",
    "wikipedia_artist": ""
  },
  "David Bowie Live Aid Performance 1": {
    "artist": "David Bowie",
    "wikidata_artist": "http://www.wikidata.org/entity/Q5383",
    "wikidata_event": "http://www.wikidata.org/entity/Q184199",
    "wikipedia_event": "https://en.wikipedia.org/wiki/Live_Aid",
    "wikipedia_artist": ""
  },
  "David Bowie Live Aid Performance 2": {
    "artist": "David Bowie",
    "wikidata_artist": "http://www.wikidata.org/entity/Q5383",
    "wikidata_event": "http://www.wikidata.org/entity/Q184199",
    "wikipedia_event": "https://en.wikipedia.org/wiki/Live_Aid",
    "wikipedia_artist": ""
  },
  "Dire Straits Live Aid Performance 1": {
    "artist": "Dire Straits",
    "wikidata_artist": "http://www.wikidata.org/entity/Q50040",
    "wikidata_event": "http://www.wikidata.org/entity/Q184199",
    "wikipedia_event": "https://en.wikipedia.org/wiki/Live_Aid",
    "wikipedia_artist": ""
  },
  "Elton John Live Aid Performance 1": {
    "artist": "Elton John",
    "wikidata_artist": "http://www.wikidata.org/entity/Q2808",
    "wikidata_event": "http://www.wikidata.org/entity/Q184199",
    "wikipedia_event": "https://en.wikipedia.org/wiki/Live_Aid",
    "wikipedia_artist": ""
  },
  "Elton John Live Aid Performance 2": {
    "artist": "Elton John",
    "wikidata_artist": "http://www.wikidata.org/entity/Q2808",
    "wikidata_event": "http://www.wikidata.org/entity/Q184199",
    "wikipedia_event": "https://en.wikipedia.org/wiki/Live_Aid",
    "wikipedia_artist": ""
  },
  "Eric Clapton Live Aid Performance 1": {
    "artist": "Eric Clapton",
    "wikidata_artist": "http://www.wikidata.org/entity/Q48187",
    "wikidata_event": "http://www.wikidata.org/entity/Q184199",
    "wikipedia_event": "https://en.wikipedia.org/wiki/Live_Aid",
    "wikipedia_artist": ""
  },
  "Led Zeppelin Live Aid Performance 1": {
    "artist": "Led Zeppelin",
    "wikidata_artist": "http://www.wikidata.org/entity/Q2331",
    "wikidata_event": "http://www.wikidata.org/entity/Q184199",
    "wikipedia_event": "https://en.wikipedia.org/wiki/Live_Aid",
    "wikipedia_artist": ""
  },
  "Madonna Live Aid Performance 1": {
    "artist": "Madonna",
    "wikidata_artist": "http://www.wikidata.org/entity/Q1744",
    "wikidata_event": "http://www.wikidata.org/entity/Q184199",
    "wikipedia_event": "https://en.wikipedia.org/wiki/Live_Aid",
    "wikipedia_artist": ""
  },
  "Paul McCartney Live Aid Performance 1": {
    "artist": "Paul McCartney",
    "wikidata_artist": "http://www.wikidata.org/entity/Q2599",
    "wikidata_event": "http://www.wikidata.org/entity/Q184199",
    "wikipedia_event": "https://en.wikipedia.org/wiki/Live_Aid",
    "wikipedia_artist": ""
  },
  "Phil Collins Live Aid Performance 1": {
    "artist": "Phil Collins",
    "wikidata_artist": "http://www.wikidata.org/entity/Q144622",
    "wikidata_event": "http://www.wikidata.org/entity/Q184199",
    "wikipedia_event": "https://en.wikipedia.org/wiki/Live_Aid",
    "wikipedia_artist": ""
  },
  "Queen Live Aid Performance 1": {
    "artist": "Queen",
    "wikidata_artist": "http://www.wikidata.org/entity/Q15862",
    "wikidata_event": "http://www.wikidata.org/entity/Q184199",
    "wikipedia_event": "https://en.wikipedia.org/wiki/Live_Aid",
    "wikipedia_artist": ""
  },
  "Queen Live Aid Performance 2": {
    "artist": "Queen",
    "wikidata_artist": "http://www.wikidata.org/entity/Q15862",
    "wikidata_event": "http://www.wikidata.org/entity/Q184199",
    "wikipedia_event": "https://en.wikipedia.org/wiki/Live_Aid",
    "wikipedia_artist": ""
  },
  "Sting Live Aid Performance 1": {
    "artist": "Sting",
    "wikidata_artist": "http://www.wikidata.org/entity/Q483203",
    "wikidata_event": "http://www.wikidata.org/entity/Q184199",
    "wikipedia_event": "https://en.wikipedia.org/wiki/Live_Aid",
    "wikipedia_artist": ""
  },
  "The Cars Live Aid Performance 1": {
    "artist": "The Cars",
    "wikidata_artist": "http://www.wikidata.org/entity/Q858388",
    "wikidata_event": "http://www.wikidata.org/entity/Q184199",
    "wikipedia_event": "https://en.wikipedia.org/wiki/Live_Aid",
    "wikipedia_artist": ""
  },
  "The Who Live Aid Performance 1": {
    "artist": "The Who",
    "wikidata_artist": "http://www.wikidata.org/entity/Q93346",
    "wikidata_event": "http://www.wikidata.org/entity/Q184199",
    "wikipedia_event": "https://en.wikipedia.org/wiki/Live_Aid",
    "wikipedia_artist": ""
  },
  "The Who Live Aid Performance 2": {
    "artist": "The Who",
    "wikidata_artist": "http://www.wikidata.org/entity/Q93346",
    "wikidata_event": "http://www.wikidata.org/entity/Q184199",
    "wikipedia_event": "https://en.wikipedia.org/wiki/Live_Aid",
    "wikipedia_artist": ""
  },
  "U2 Live Aid Performance 1": {
    "artist": "U2",
    "wikidata_artist": "http://www.wikidata.org/entity/Q396",
    "wikidata_event": "http://www.wikidata.org/entity/Q184199",
    "wikipedia_event": "https://en.wikipedia.org/wiki/Live_Aid",
    "wikipedia_artist": ""
  },
  "U2 Live Aid Performance 2": {
    "artist": "U2",
    "wikidata_artist": "http://www.wikidata.org/entity/Q396",
    "wikidata_event": "http://www.wikidata.org/entity/Q184199",
    "wikipedia_event": "https://en.wikipedia.org/wiki/Live_Aid",
    "wikipedia_artist": ""
  }
}